gifi/main.py
gifi/queue.py
gifi/command.py
gifi/feature.py
gifi/slack.py
gifi/git_hub.py
gifi/__init__.py
gifi/internal/git_utils.py
gifi/internal/configuration.py
gifi/internal/__init__.py
gifi/utils/git_utils.py
gifi/utils/configuration.py
gifi/utils/__init__.py
git_gifi-0.10.dist-info/RECORD
git_gifi-0.10.dist-info/metadata.json
git_gifi-0.10.dist-info/METADATA
git_gifi-0.10.dist-info/entry_points.txt
git_gifi-0.10.dist-info/DESCRIPTION.rst
git_gifi-0.10.dist-info/top_level.txt
git_gifi-0.10.dist-info/WHEEL
