Metadata-Version: 1.0
Name: git-gifi
Version: 0.10
Summary: Git and github enhancements to git.
Home-page: https://github.com/kokosing/git-gifi
Author: Grzegorz Kokosinski
Author-email: g.kokosinski a) gmail.com
License: UNKNOWN
Keywords: git github pull request slack
Platform: UNKNOWN
